routerific/__init__.py
routerific/router.py
routerific/tests/__init__.py
routerific/tests/test_dispatch.py
django_routerific-0.2.0.dist-info/LICENSE
django_routerific-0.2.0.dist-info/WHEEL
django_routerific-0.2.0.dist-info/METADATA
django_routerific-0.2.0.dist-info/RECORD
